[
    {
        "title": " learn backend ",
        "description": "express js node js",
        "isChecked": false,
        "id": 1,
        "userid": "1"
    },
    {
        "title": " learn fronted ",
        "description": "react js node js",
        "isChecked": false,
        "id": 2,
        "userid": "2"
    },
    {
        "title": " learn fronted 2 ",
        "description": "react js node js 2",
        "isChecked": false,
        "id": 3,
        "userid": "2"
    },
    {
        "title": " learn fronted 3 ",
        "description": "react js node js 3",
        "isChecked": false,
        "id": 4,
        "userid": "2"
    }
]